cryptools/__init__.py
cryptools/aes.py
cryptools/cipher_repeating_key_xor.py
cryptools/md4.py
cryptools/rsa.py
cryptools/sha1.py
cryptools/xor.py
cryptools/attack/__init__.py
cryptools/attack/attack_cbc_padding_oracle.py
cryptools/attack/attack_repeating_key_xor.py
cryptools/attack/attack_single_byte_xor.py
cryptools/cipher/__init__.py
cryptools/cipher/aes.py
cryptools/cipher/cipher_repeating_key_xor.py
cryptools/cipher/rsa.py
cryptools/cipher/xor.py
cryptools/prng/__init__.py
cryptools/prng/mt19937.py
cryptools/util/__init__.py
cryptools/util/generate_key.py
cryptools/util/pad.py
cryptools-0.0.6.dist-info/LICENSE
cryptools-0.0.6.dist-info/METADATA
cryptools-0.0.6.dist-info/WHEEL
cryptools-0.0.6.dist-info/top_level.txt
cryptools-0.0.6.dist-info/RECORD
