Metadata-Version: 2.1
Name: cryptools
Version: 0.0.6
Summary: easy-to-use implementations for ciphers, hashes, prngs, and attacks
Home-page: https://github.com/adbforlife/cryptools.git
Author: adbforlife
Author-email: adbforlife2018@gmail.com
License: UNKNOWN
Platform: UNKNOWN
Classifier: Programming Language :: Python :: 3
Classifier: License :: OSI Approved :: MIT License
Classifier: Operating System :: OS Independent
Requires-Python: >=3.4
Requires-Dist: scipy
Requires-Dist: pycryptodome
